packUpdate/__init__.py
packUpdate/updatePackages.py
packUpdate/services/__init__.py
packUpdate/services/automation_service.py
packUpdate/services/cleanup_service.py
packUpdate/services/interactive_service.py
packUpdate/services/package_service.py
packUpdate/services/report_service.py
packUpdate/services/version_service.py
packUpdate/utils/__init__.py
packUpdate/utils/cli.py
packUpdate/utils/logger.py
packUpdate/utils/version.py
tests/__init__.py
tests/test_cli.py
tests/test_imports.py
tests/test_integration.py
tests/test_safe_mode.py
tests/test_update_packages.py
tests/test_version.py
packupdate-1.1.4.dist-info/LICENSE
packupdate-1.1.4.dist-info/METADATA
packupdate-1.1.4.dist-info/WHEEL
packupdate-1.1.4.dist-info/entry_points.txt
packupdate-1.1.4.dist-info/top_level.txt
packupdate-1.1.4.dist-info/RECORD
