Metadata-Version: 2.1
Name: packupdate
Version: 1.1.4
Summary: A Python utility to update Node.js project dependencies safely with interactive mode and version management.
Home-page: https://github.com/sthpratik/PackUpdate
Author: Manish Shrestha
Author-email: sth.pratik@gmail.com
Classifier: Programming Language :: Python :: 3
Classifier: License :: OSI Approved :: MIT License
Classifier: Operating System :: OS Independent
Requires-Python: >=3.8
License-File: LICENSE
Requires-Dist: inquirer>=2.10.0
Requires-Dist: requests>=2.25.0
